pysnmp/__init__.py
pysnmp/cache.py
pysnmp/debug.py
pysnmp/error.py
pysnmp/nextid.py
pysnmp/carrier/__init__.py
pysnmp/carrier/base.py
pysnmp/carrier/error.py
pysnmp/carrier/sockfix.py
pysnmp/carrier/sockmsg.py
pysnmp/carrier/asyncio/__init__.py
pysnmp/carrier/asyncio/base.py
pysnmp/carrier/asyncio/dispatch.py
pysnmp/carrier/asyncio/dgram/__init__.py
pysnmp/carrier/asyncio/dgram/base.py
pysnmp/carrier/asyncio/dgram/udp.py
pysnmp/carrier/asyncio/dgram/udp6.py
pysnmp/carrier/asyncore/__init__.py
pysnmp/carrier/asyncore/base.py
pysnmp/carrier/asyncore/dispatch.py
pysnmp/carrier/asyncore/dgram/__init__.py
pysnmp/carrier/asyncore/dgram/base.py
pysnmp/carrier/asyncore/dgram/udp.py
pysnmp/carrier/asyncore/dgram/udp6.py
pysnmp/carrier/asyncore/dgram/unix.py
pysnmp/carrier/twisted/__init__.py
pysnmp/carrier/twisted/base.py
pysnmp/carrier/twisted/dispatch.py
pysnmp/carrier/twisted/dgram/__init__.py
pysnmp/carrier/twisted/dgram/base.py
pysnmp/carrier/twisted/dgram/udp.py
pysnmp/carrier/twisted/dgram/unix.py
pysnmp/entity/__init__.py
pysnmp/entity/config.py
pysnmp/entity/engine.py
pysnmp/entity/observer.py
pysnmp/entity/rfc3413/__init__.py
pysnmp/entity/rfc3413/cmdgen.py
pysnmp/entity/rfc3413/cmdrsp.py
pysnmp/entity/rfc3413/config.py
pysnmp/entity/rfc3413/context.py
pysnmp/entity/rfc3413/ntforg.py
pysnmp/entity/rfc3413/ntfrcv.py
pysnmp/hlapi/__init__.py
pysnmp/hlapi/transport.py
pysnmp/hlapi/varbinds.py
pysnmp/hlapi/v1arch/__init__.py
pysnmp/hlapi/v1arch/auth.py
pysnmp/hlapi/v1arch/dispatch.py
pysnmp/hlapi/v1arch/asyncio/__init__.py
pysnmp/hlapi/v1arch/asyncio/cmdgen.py
pysnmp/hlapi/v1arch/asyncio/dispatch.py
pysnmp/hlapi/v1arch/asyncio/ntforg.py
pysnmp/hlapi/v1arch/asyncio/transport.py
pysnmp/hlapi/v1arch/asyncore/__init__.py
pysnmp/hlapi/v1arch/asyncore/cmdgen.py
pysnmp/hlapi/v1arch/asyncore/dispatch.py
pysnmp/hlapi/v1arch/asyncore/ntforg.py
pysnmp/hlapi/v1arch/asyncore/transport.py
pysnmp/hlapi/v1arch/asyncore/sync/__init__.py
pysnmp/hlapi/v1arch/asyncore/sync/cmdgen.py
pysnmp_bw-5.0.3.dist-info/LICENSE.rst
pysnmp_bw-5.0.3.dist-info/METADATA
pysnmp_bw-5.0.3.dist-info/WHEEL
pysnmp_bw-5.0.3.dist-info/top_level.txt
pysnmp_bw-5.0.3.dist-info/zip-safe
pysnmp_bw-5.0.3.dist-info/RECORD
