Metadata-Version: 2.1
Name: pysnmp-bw
Version: 5.0.3
Summary: SNMP library for Python
Home-page: https://github.com/BurgundyWillow/pysnmp
Author: Ilya Etingof
Author-email: etingof@gmail.com
Maintainer: BurgundyWillow
License: BSD-2-Clause
Platform: any
Classifier: Development Status :: 5 - Production/Stable
Classifier: Environment :: Console
Classifier: Intended Audience :: Developers
Classifier: Intended Audience :: Education
Classifier: Intended Audience :: Information Technology
Classifier: Intended Audience :: System Administrators
Classifier: Intended Audience :: Telecommunications Industry
Classifier: License :: OSI Approved :: BSD License
Classifier: Natural Language :: English
Classifier: Operating System :: OS Independent
Classifier: Programming Language :: Python :: 2
Classifier: Programming Language :: Python :: 2.6
Classifier: Programming Language :: Python :: 2.7
Classifier: Programming Language :: Python :: 3
Classifier: Programming Language :: Python :: 3.2
Classifier: Programming Language :: Python :: 3.3
Classifier: Programming Language :: Python :: 3.4
Classifier: Programming Language :: Python :: 3.5
Classifier: Programming Language :: Python :: 3.6
Classifier: Programming Language :: Python :: 3.7
Classifier: Topic :: Communications
Classifier: Topic :: System :: Monitoring
Classifier: Topic :: System :: Networking :: Monitoring
Classifier: Topic :: Software Development :: Libraries :: Python Modules
License-File: LICENSE.rst
Requires-Dist: pysmi
Requires-Dist: pysnmpcrypto
Requires-Dist: pyasn1 (>=0.2.3)
Requires-Dist: ordereddict ; python_version < "2.7"
